{
  "node_modules/.pnpm/@sveltejs+kit@1.0.0-next.470_svelte@3.50.0+vite@3.1.0/node_modules/@sveltejs/kit/src/runtime/client/start.js": {
    "file": "_app/immutable/start-912365e5.js",
    "src": "node_modules/.pnpm/@sveltejs+kit@1.0.0-next.470_svelte@3.50.0+vite@3.1.0/node_modules/@sveltejs/kit/src/runtime/client/start.js",
    "isEntry": true,
    "imports": [
      "_index-c18d4107.js",
      "_singletons-993395f8.js"
    ],
    "dynamicImports": [
      ".svelte-kit/generated/nodes/0.js",
      ".svelte-kit/generated/nodes/1.js",
      ".svelte-kit/generated/nodes/2.js"
    ]
  },
  "node_modules/.pnpm/@sveltejs+kit@1.0.0-next.470_svelte@3.50.0+vite@3.1.0/node_modules/@sveltejs/kit/src/runtime/components/layout.svelte": {
    "file": "_app/immutable/components/layout.svelte-b9877645.js",
    "src": "node_modules/.pnpm/@sveltejs+kit@1.0.0-next.470_svelte@3.50.0+vite@3.1.0/node_modules/@sveltejs/kit/src/runtime/components/layout.svelte",
    "isEntry": true,
    "imports": [
      "_index-c18d4107.js"
    ]
  },
  "src/routes/+error.svelte": {
    "file": "_app/immutable/components/pages/_error.svelte-18b1391f.js",
    "src": "src/routes/+error.svelte",
    "isEntry": true,
    "imports": [
      "_index-c18d4107.js",
      "_singletons-993395f8.js"
    ],
    "css": [
      "_app/immutable/assets/_error-30c56eab.css",
      "_app/immutable/assets/ress-39fe2769.css"
    ]
  },
  "src/routes/+page.svelte": {
    "file": "_app/immutable/components/pages/_page.svelte-23dcde5a.js",
    "src": "src/routes/+page.svelte",
    "isEntry": true,
    "imports": [
      "_index-c18d4107.js"
    ],
    "css": [
      "_app/immutable/assets/_page-85cdca2c.css",
      "_app/immutable/assets/ress-39fe2769.css"
    ]
  },
  "_singletons-993395f8.js": {
    "file": "_app/immutable/chunks/singletons-993395f8.js",
    "imports": [
      "_index-c18d4107.js"
    ]
  },
  "_index-c18d4107.js": {
    "file": "_app/immutable/chunks/index-c18d4107.js"
  },
  ".svelte-kit/generated/nodes/0.js": {
    "file": "_app/immutable/chunks/0-733e565f.js",
    "src": ".svelte-kit/generated/nodes/0.js",
    "isDynamicEntry": true,
    "imports": [
      "node_modules/.pnpm/@sveltejs+kit@1.0.0-next.470_svelte@3.50.0+vite@3.1.0/node_modules/@sveltejs/kit/src/runtime/components/layout.svelte"
    ]
  },
  ".svelte-kit/generated/nodes/1.js": {
    "file": "_app/immutable/chunks/1-8ba9d58e.js",
    "src": ".svelte-kit/generated/nodes/1.js",
    "isDynamicEntry": true,
    "imports": [
      "src/routes/+error.svelte"
    ]
  },
  ".svelte-kit/generated/nodes/2.js": {
    "file": "_app/immutable/chunks/2-123dbda0.js",
    "src": ".svelte-kit/generated/nodes/2.js",
    "isDynamicEntry": true,
    "imports": [
      "src/routes/+page.svelte"
    ]
  },
  "src/routes/+error.css": {
    "file": "_app/immutable/assets/_error-30c56eab.css",
    "src": "src/routes/+error.css"
  },
  "src/routes/+page.css": {
    "file": "_app/immutable/assets/_page-85cdca2c.css",
    "src": "src/routes/+page.css"
  },
  "ress.css": {
    "file": "_app/immutable/assets/ress-39fe2769.css",
    "src": "ress.css"
  }
}